pop_aiohttp/conf.py
pop_aiohttp/version.py
pop_aiohttp/acct/request/basic_auth.py
pop_aiohttp/exec/request/init.py
pop_aiohttp/exec/request/json_request.py
pop_aiohttp/exec/request/raw.py
pop_aiohttp/server/web.py
pop_aiohttp/tool/request/application.py
pop_aiohttp/tool/request/session.py
pop_aiohttp/tool/type/dict.py
pop_aiohttp-1.2.0.dist-info/LICENSE
pop_aiohttp-1.2.0.dist-info/METADATA
pop_aiohttp-1.2.0.dist-info/WHEEL
pop_aiohttp-1.2.0.dist-info/entry_points.txt
pop_aiohttp-1.2.0.dist-info/top_level.txt
pop_aiohttp-1.2.0.dist-info/RECORD
